Metadata-Version: 2.1
Name: qlik-test-dani
Version: 0.1.0
Summary: 
Author: Your Name
Author-email: you@example.com
Requires-Python: >=3.11.2,<4.0.0
Classifier: Programming Language :: Python :: 3
Requires-Dist: pandas (>=1.5.3,<2.0.0)
